{
  "annotations": {
    "changelogDate": "20240105223746"
  },
  "applications": "*",
  "entityTableName": "user_profile",
  "fields": [
    {
      "fieldName": "userName",
      "fieldType": "String"
    },
    {
      "fieldName": "firstName",
      "fieldType": "String"
    },
    {
      "fieldName": "lastName",
      "fieldType": "String"
    },
    {
      "fieldName": "email",
      "fieldType": "String"
    }
  ],
  "name": "UserProfile",
  "relationships": [
    {
      "otherEntityName": "playlist",
      "relationshipName": "playlist",
      "relationshipSide": "left",
      "relationshipType": "one-to-one"
    },
    {
      "otherEntityName": "comment",
      "otherEntityRelationshipName": "postedBy",
      "relationshipName": "comments",
      "relationshipSide": "left",
      "relationshipType": "one-to-many"
    }
  ],
  "searchEngine": "no"
}
